CONTRIBUTORS.rst
LICENSE.rst
MANIFEST.in
README.rst
requirements.txt
setup.py
webgears/__init__.py
webgears/__init__.pyc
webgears/application.py
webgears/application.pyc
webgears/errors.py
webgears/errors.pyc
webgears/json.py
webgears/json.pyc
webgears/routing.py
webgears/routing.pyc
webgears/views.py
webgears/views.pyc
webgears.egg-info/PKG-INFO
webgears.egg-info/SOURCES.txt
webgears.egg-info/dependency_links.txt
webgears.egg-info/requires.txt
webgears.egg-info/top_level.txt
webgears.egg-info/zip-safe