Metadata-Version: 1.1
Name: webgears
Version: 0.0.7
Summary: Python web framework
Home-page: https://github.com/ets-labs/webgears
Author: ETS Labs
Author-email: rmogilatov@gmail.com
License: BSD New
Platform: UNKNOWN
Classifier: Development Status :: 2 - Pre-Alpha
Classifier: Intended Audience :: Developers
Classifier: License :: OSI Approved :: BSD License
Classifier: Programming Language :: Python
Classifier: Programming Language :: Python :: 2
Classifier: Programming Language :: Python :: 2.7
Classifier: Programming Language :: Python :: Implementation :: CPython
Classifier: Topic :: Software Development
Classifier: Topic :: Software Development :: Libraries
Classifier: Topic :: Software Development :: Libraries :: Python Modules
